ndex_webapp_python_exporters/__init__.py
ndex_webapp_python_exporters/exporters.py
ndex_webapp_python_exporters/ndex_exporters.py
ndex_webapp_python_exporters-0.1.1.data/scripts/ndex_exporters.py
ndex_webapp_python_exporters-0.1.1.dist-info/AUTHORS.rst
ndex_webapp_python_exporters-0.1.1.dist-info/METADATA
ndex_webapp_python_exporters-0.1.1.dist-info/WHEEL
ndex_webapp_python_exporters-0.1.1.dist-info/top_level.txt
ndex_webapp_python_exporters-0.1.1.dist-info/RECORD
