Metadata-Version: 2.1
Name: ndex-webapp-python-exporters
Version: 0.1.1
Summary: Command line exporters written in Python used by the NDex REST service
Home-page: https://github.com/ndexbio/ndex_webapp_python_exporters
Author: Chris Churas
Author-email: churas.camera@gmail.com
License: BSD license
Keywords: ndex_webapp_python_exporters
Platform: UNKNOWN
Classifier: Development Status :: 2 - Pre-Alpha
Classifier: Intended Audience :: Developers
Classifier: License :: OSI Approved :: BSD License
Classifier: Natural Language :: English
Classifier: Programming Language :: Python :: 3.5
Classifier: Programming Language :: Python :: 3.6
Classifier: Programming Language :: Python :: 3.7
Requires-Dist: argparse
Requires-Dist: ndex2
